millistream_mdf/__init__.py
millistream_mdf/_constants.py
millistream_mdf/_libmdf.py
millistream_mdf/_mappings.py
millistream_mdf/async_client.py
millistream_mdf/exceptions.py
millistream_mdf/install_deps.py
millistream_mdf/message.py
millistream_mdf/message_builder.py
millistream_mdf/sync_client.py
millistream_mdf/types.py
millistream_mdf-0.1.11.dist-info/METADATA
millistream_mdf-0.1.11.dist-info/WHEEL
millistream_mdf-0.1.11.dist-info/top_level.txt
millistream_mdf-0.1.11.dist-info/RECORD
