Metadata-Version: 2.4
Name: millistream-mdf
Version: 0.1.11
Summary: A high-level Python wrapper for the libmdf C SDK, providing access to the Millistream Data Feed (MDF) for real-time financial data streaming.
Author-email: Gustav Frison <gustav.frison@millistream.com>
Project-URL: Homepage, https://github.com/mint273/millistream-mdf
Project-URL: Repository, https://github.com/mint273/millistream-mdf
Project-URL: Documentation, https://packages.millistream.com/documents/
Project-URL: Issues, https://github.com/mint273/millistream-mdf/issues
Project-URL: Bug Reports, https://github.com/mint273/millistream-mdf/issues
Project-URL: Source Code, https://github.com/mint273/millistream-mdf
Keywords: millistream,mdf,data feed,financial data,real-time data
Requires-Python: >=3.12
Requires-Dist: docker>=7.1.0
Requires-Dist: pytest>=8.4.2
Requires-Dist: rich>=14.2.0
Requires-Dist: websockets>=15.0.1
